setup.py
singer_tools.egg-info/PKG-INFO
singer_tools.egg-info/SOURCES.txt
singer_tools.egg-info/dependency_links.txt
singer_tools.egg-info/entry_points.txt
singer_tools.egg-info/requires.txt
singer_tools.egg-info/top_level.txt
singertools/__init__.py
singertools/check_tap.py
singertools/infer_schema.py
singertools/release.py