Metadata-Version: 1.1
Name: singer-tools
Version: 0.3.0
Summary: Tools for working with Singer.io Taps and Targets
Home-page: http://singer.io
Author: Stitch
Author-email: UNKNOWN
License: UNKNOWN
Platform: UNKNOWN
Classifier: Programming Language :: Python :: 3 :: Only
